CHANGELOG.rst
LICENSE.txt
MANIFEST.in
README.rst
THANKS.txt
setup.cfg
setup.py
easymunk/__init__.py
easymunk/_version.py
easymunk/cp.py
easymunk/drawing.py
easymunk/extension_build.py
easymunk/functions.py
easymunk/py.typed
easymunk/typing.py
easymunk/util.py
easymunk/abc/__init__.py
easymunk/abc/cffi_base.py
easymunk/abc/game_object.py
easymunk/abc/has_bb_mixin.py
easymunk/abc/ipython_renderer.py
easymunk/core/__init__.py
easymunk/core/arbiter.py
easymunk/core/body.py
easymunk/core/collision_handler.py
easymunk/core/constraints.py
easymunk/core/junction.py
easymunk/core/shapes.py
easymunk/core/space.py
easymunk/examples/__init__.py
easymunk/examples/e01_basic.py
easymunk/geometry/__init__.py
easymunk/geometry/autogeometry.py
easymunk/geometry/geometry.py
easymunk/linalg/__init__.py
easymunk/linalg/mat22.py
easymunk/linalg/math.py
easymunk/linalg/transform.py
easymunk/linalg/vec2d.py
easymunk/matplotlib/__init__.py
easymunk/matplotlib/draw_options.py
easymunk/pygame/__init__.py
easymunk/pygame/draw_options.py
easymunk/pyglet/__init__.py
easymunk/pyglet/draw_options.py
easymunk/pyxel/__init__.py
easymunk/pyxel/bodies.py
easymunk/pyxel/camera.py
easymunk/pyxel/draw_options.py
easymunk/pyxel/helpers.py
easymunk/pyxel/mock.py
easymunk/pyxel/utilities.py
easymunk/streamlit/__init__.py
easymunk/streamlit/core.py
easymunk/testing/__init__.py
easymunk/testing/base_cases.py
easymunk/testing/deep_compare.py
easymunk/testing/strategies.py
easymunk/testing/utils.py
easymunk/types/__init__.py
easymunk/types/bb.py
easymunk/types/collections.py
easymunk/types/contact_point_set.py
easymunk/types/query_info.py
easymunk/types/shape_filter.py
easymunk/utilities/__init__.py
easymunk/utilities/svg_path.py
easymunk_physics.egg-info/PKG-INFO
easymunk_physics.egg-info/SOURCES.txt
easymunk_physics.egg-info/dependency_links.txt
easymunk_physics.egg-info/requires.txt
easymunk_physics.egg-info/top_level.txt
examples/arrows.py
examples/autogeometry.py
examples/balls_and_lines.py
examples/basic_test.py
examples/bouncing_balls.py
examples/box2d_pyramid.py
examples/box2d_vertical_stack.py
examples/breakout.py
examples/constraints.py
examples/contact_and_no_flipy.py
