Metadata-Version: 2.1
Name: easymunk-physics
Version: 0.9.2
Summary: Easymunk is a easy-to-use pythonic 2d physics library
Home-page: http://fabiommendes.github.io/easymunk/
Author: Fábio Mendes
Author-email: fabiomacedomendes@gmail.com
License: MIT License
Platform: UNKNOWN
Classifier: Development Status :: 4 - Beta
Classifier: Intended Audience :: Developers
Classifier: License :: OSI Approved :: MIT License
Classifier: Operating System :: OS Independent
Classifier: Programming Language :: Python
Classifier: Topic :: Games/Entertainment
Classifier: Topic :: Scientific/Engineering :: Physics
Classifier: Topic :: Software Development :: Libraries
Classifier: Topic :: Software Development :: Libraries :: pygame
Classifier: Programming Language :: Python :: 3
Classifier: Programming Language :: Python :: 3.8
Classifier: Programming Language :: Python :: 3.9
Classifier: Programming Language :: Python :: 3.10
Requires-Python: >=3.8
Provides-Extra: dev
Provides-Extra: docs
Provides-Extra: backends
